calcalc/CalCalc.py
calcalc/__init__.py
calcalc-0.0.2.dist-info/LICENSE.txt
calcalc-0.0.2.dist-info/METADATA
calcalc-0.0.2.dist-info/WHEEL
calcalc-0.0.2.dist-info/top_level.txt
calcalc-0.0.2.dist-info/RECORD
