Metadata-Version: 2.1
Name: calcalc
Version: 0.0.2
Summary: CalCalc package.
Home-page: http://github.com/caseylam/calcalc
Author: Casey Lam
Author-email: casey_lam@berkeley.edu
License: BSD
Keywords: homework
Platform: any
Classifier: Development Status :: 3 - Alpha
Classifier: Intended Audience :: Education
Classifier: Topic :: Software Development :: Libraries :: Python Modules
Classifier: License :: OSI Approved :: BSD License
Classifier: Programming Language :: Python :: 3.9
Requires-Python: >=3
License-File: LICENSE.txt
